alphapulldown_input_parser/__init__.py
alphapulldown_input_parser/parser.py
alphapulldown_input_parser-0.2.0.dist-info/licenses/LICENSE
alphapulldown_input_parser-0.2.0.dist-info/METADATA
alphapulldown_input_parser-0.2.0.dist-info/WHEEL
alphapulldown_input_parser-0.2.0.dist-info/top_level.txt
alphapulldown_input_parser-0.2.0.dist-info/RECORD
